nlpia_bot/__init__.py
nlpia_bot/bert_language_model.py
nlpia_bot/clibot.py
nlpia_bot/constants.py
nlpia_bot/qa_example.py
nlpia_bot/qa_train.py
nlpia_bot/spacy_language_model.py
nlpia_bot/template_generators.py
nlpia_bot/etl/elastic.py
nlpia_bot/etl/faqs.py
nlpia_bot/etl/glossaries.py
nlpia_bot/etl/journal.py
nlpia_bot/etl/knowledge_extraction.py
nlpia_bot/etl/qa_datasets.py
nlpia_bot/etl/qcembed.py
nlpia_bot/etl/scrape_wikipedia.py
nlpia_bot/etl/vectors.py
nlpia_bot/etl/wiktionary.py
nlpia_bot/etl/yml.py
nlpia_bot/plugins/ircbot.py
nlpia_bot/scores/quality_score.py
nlpia_bot/scores/semantics_score.py
nlpia_bot/scores/sentiment_score.py
nlpia_bot/scores/spell_score.py
nlpia_bot/skills/elastic_bots.py
nlpia_bot/skills/eliza_bots.py
nlpia_bot/skills/faq_bots.py
nlpia_bot/skills/glossary_bots.py
nlpia_bot/skills/juan_bots.py
nlpia_bot/skills/nima_bots.py
nlpia_bot/skills/parul_bots.py
nlpia_bot/skills/pattern_bots.py
nlpia_bot/skills/qa_bots.py
nlpia_bot/skills/qa_models.py
nlpia_bot/skills/qa_utils.py
nlpia_bot/skills/search_fuzzy_bots.py
nlpia_bot/skills/search_use_bots.py
nlpia_bot/skills/time_bots.py
nlpia_bot-0.2.14.dist-info/AUTHORS.md
nlpia_bot-0.2.14.dist-info/LICENSE.txt
nlpia_bot-0.2.14.dist-info/METADATA
nlpia_bot-0.2.14.dist-info/WHEEL
nlpia_bot-0.2.14.dist-info/entry_points.txt
nlpia_bot-0.2.14.dist-info/top_level.txt
nlpia_bot-0.2.14.dist-info/RECORD
