Metadata-Version: 2.1
Name: nlpia-bot
Version: 0.2.14
Summary: "An open framework and dataset for building a distributed-agent chatbot based on _Natural Language Processing in Action_."
Home-page: https://nlpia.org
Author: hobs
Author-email: hobs+github@totalgood.com
License: mit
Platform: any
Classifier: Development Status :: 4 - Beta
Classifier: Programming Language :: Python
Classifier: Programming Language :: Python :: 3.7
Classifier: Environment :: Console
Classifier: Intended Audience :: Developers
Classifier: License :: OSI Approved :: MIT License
Classifier: Operating System :: OS Independent
Classifier: Topic :: Software Development :: Libraries :: Python Modules
Classifier: Topic :: Text Processing :: Linguistic
Classifier: Topic :: Text Processing :: Filters
Classifier: Topic :: Text Processing :: General
Classifier: Topic :: Text Processing :: Indexing
Classifier: Topic :: Scientific/Engineering :: Mathematics
Classifier: Topic :: Scientific/Engineering :: Artificial Intelligence
Requires-Dist: boto3
Requires-Dist: ConfigArgParse
Requires-Dist: fuzzywuzzy
Requires-Dist: gitpython
Requires-Dist: lxml
Requires-Dist: nltk
Requires-Dist: pandas
Requires-Dist: pre-commit
Requires-Dist: psycopg2
Requires-Dist: regex
Requires-Dist: seaborn
Requires-Dist: spacy (<2.3.0,>=2.2.2)
Requires-Dist: scikit-learn
Requires-Dist: scipy
Requires-Dist: tensorboardX
Requires-Dist: tensorflow
Requires-Dist: torch
Requires-Dist: transformers (<2.5.0,>=2.4.1)
Requires-Dist: wikipedia-api
Requires-Dist: environment
Provides-Extra: django
Requires-Dist: celery ; extra == 'django'
Requires-Dist: cookiecutter ; extra == 'django'
Requires-Dist: django ; extra == 'django'
Requires-Dist: channels ; extra == 'django'
Requires-Dist: django-extensions ; extra == 'django'
Provides-Extra: keras
Requires-Dist: keras ; extra == 'keras'
Provides-Extra: pytorch
Requires-Dist: torch ; extra == 'pytorch'
Provides-Extra: testing
Requires-Dist: pytest ; extra == 'testing'
Requires-Dist: pytest-cov ; extra == 'testing'
